baidu_sign/__init__.py
baidu_sign/baidu_sign.py
baidu_sign/js2py_sign.py
baidu_sign-0.1.0.dist-info/WHEEL
baidu_sign-0.1.0.dist-info/METADATA
baidu_sign-0.1.0.dist-info/licenses/LICENSE
baidu_sign-0.1.0.dist-info/RECORD
