Metadata-Version: 2.1
Name: baidu-sign
Version: 0.1.0
Summary: Sign text for baidu fanyi
License: MIT
Author-email: ffreemt <yucongo+fmt@gmail.com>
Requires-Python: >=3.8
Requires-Dist: google-sign>=0.0.2
Requires-Dist: js2py>=0.74
